Metadata-Version: 1.0
Name: sqlatom
Version: 0.1.0
Summary: Useful wrapper on sql command
Home-page: UNKNOWN
Author: shangshuaipeng
Author-email: UNKNOWN
License: UNKNOWN
Platform: UNKNOWN
